[
    {
        "n": "Nozomi 95",
        "d": "Down",
        "b": true,
        "s": "NISHI-AKASHI",
        "s_b": "HIMEJI"
    },
    {
        "n": "Nozomi 89",
        "d": "Down",
        "b": true,
        "s": "HIGASHIHIROSHIMA",
        "s_b": "HIROSHIMA"
    },
    {
        "n": "Nozomi 59",
        "d": "Down",
        "b": true,
        "s": "KOKURA",
        "s_b": "HAKATA"
    },
    {
        "n": "Tsurugi 50",
        "d": "Up",
        "b": true,
        "s": "SHIN-TAKAOKA",
        "s_b": "TOYAMA"
    },
    {
        "n": "Tsurugi 63",
        "d": "Down",
        "b": true,
        "s": "SHIN-TAKAOKA",
        "s_b": "KANAZAWA"
    },
    {
        "n": "Tsubame 342",
        "d": "Up",
        "b": true,
        "s": "SHIN-YATSUSHIRO",
        "s_b": "KUMAMOTO"
    },
    {
        "n": "Sakura 410",
        "d": "Up",
        "b": true,
        "s": "SHIN-TOSU",
        "s_b": "HAKATA"
    },
    {
        "n": "Sakura 483",
        "d": "Down",
        "b": true,
        "s": "SHIN-OMUTA",
        "s_b": "SHIN-TAMANA"
    },
    {
        "n": "Sakura 773",
        "d": "Down",
        "b": true,
        "s": "SHIN-TAMANA",
        "s_b": "KUMAMOTO"
    },
    {
        "n": "Tsubame 343",
        "d": "Down",
        "b": false,
        "s": "SENDAI"
    }
]