[
    {
        "n": "Nozomi 64",
        "d": "Up",
        "b": true,
        "s": "SHINAGAWA",
        "s_b": "TOKYO"
    },
    {
        "n": "Hikari 669",
        "d": "Down",
        "b": true,
        "s": "MIKAWA-ANJO",
        "s_b": "NAGOYA"
    },
    {
        "n": "Nozomi 95",
        "d": "Down",
        "b": true,
        "s": "NISHI-AKASHI",
        "s_b": "HIMEJI"
    },
    {
        "n": "Nozomi 89",
        "d": "Down",
        "b": true,
        "s": "HIGASHIHIROSHIMA",
        "s_b": "HIROSHIMA"
    },
    {
        "n": "Nozomi 59",
        "d": "Down",
        "b": true,
        "s": "KOKURA",
        "s_b": "HAKATA"
    },
    {
        "n": "Tsurugi 63",
        "d": "Down",
        "b": true,
        "s": "SHIN-TAKAOKA",
        "s_b": "KANAZAWA"
    },
    {
        "n": "Tsubame 342",
        "d": "Up",
        "b": true,
        "s": "SHIN-YATSUSHIRO",
        "s_b": "KUMAMOTO"
    },
    {
        "n": "Sakura 410",
        "d": "Up",
        "b": true,
        "s": "SHIN-TOSU",
        "s_b": "HAKATA"
    },
    {
        "n": "Tsubame 343",
        "d": "Down",
        "b": true,
        "s": "SENDAI",
        "s_b": "KAGOSHIMA-CHUO"
    }
]