[
    {
        "n": "Sakura 764",
        "d": "Up",
        "b": true,
        "s": "HAKATA",
        "s_b": "KOKURA"
    },
    {
        "n": "Kodama 962",
        "d": "Up",
        "b": true,
        "s": "HAKATA",
        "s_b": "KOKURA"
    },
    {
        "n": "Nozomi 190",
        "d": "Up",
        "b": true,
        "s": "KOKURA",
        "s_b": "SHIN-SHIMONOSEKI"
    },
    {
        "n": "Nozomi 50",
        "d": "Up",
        "b": true,
        "s": "SHIN-SHIMONOSEKI",
        "s_b": "ASA"
    },
    {
        "n": "Sakura 762",
        "d": "Up",
        "b": true,
        "s": "ASA",
        "s_b": "SHIN-YAMAGUCHI"
    },
    {
        "n": "Kodama 960",
        "d": "Up",
        "b": true,
        "s": "SHIN-YAMAGUCHI",
        "s_b": "TOKUYAMA"
    },
    {
        "n": "Nozomi 48",
        "d": "Up",
        "b": false,
        "s": "TOKUYAMA"
    },
    {
        "n": "Sakura 764",
        "d": "Down",
        "b": true,
        "s": "HAKATA",
        "s_b": "KOKURA"
    },
    {
        "n": "Kodama 962",
        "d": "Down",
        "b": true,
        "s": "HAKATA",
        "s_b": "KOKURA"
    },
    {
        "n": "Nozomi 190",
        "d": "Down",
        "b": true,
        "s": "KOKURA",
        "s_b": "SHIN-SHIMONOSEKI"
    },
    {
        "n": "Nozomi 50",
        "d": "Down",
        "b": true,
        "s": "SHIN-SHIMONOSEKI",
        "s_b": "ASA"
    },
    {
        "n": "Sakura 762",
        "d": "Down",
        "b": true,
        "s": "ASA",
        "s_b": "SHIN-YAMAGUCHI"
    },
    {
        "n": "Kodama 960",
        "d": "Down",
        "b": true,
        "s": "SHIN-YAMAGUCHI",
        "s_b": "TOKUYAMA"
    },
    {
        "n": "Nozomi 48",
        "d": "Down",
        "b": false,
        "s": "TOKUYAMA"
    },
    {
        "n": "Nozomi 104",
        "d": "Down",
        "b": true,
        "s": "SHIN-IWAKUNI",
        "s_b": "HIROSHIMA"
    },
    {
        "n": "Nozomi 46",
        "d": "Down",
        "b": true,
        "s": "SHIN-IWAKUNI",
        "s_b": "HIROSHIMA"
    },
    {
        "n": "Sakura 760",
        "d": "Down",
        "b": true,
        "s": "HIROSHIMA",
        "s_b": "HIGASHIHIROSHIMA"
    },
    {
        "n": "Nozomi 184",
        "d": "Down",
        "b": true,
        "s": "HIGASHIHIROSHIMA",
        "s_b": "MIHARA"
    },
    {
        "n": "Kodama 958",
        "d": "Down",
        "b": true,
        "s": "HIGASHIHIROSHIMA",
        "s_b": "MIHARA"
    },
    {
        "n": "Nozomi 44",
        "d": "Down",
        "b": true,
        "s": "MIHARA",
        "s_b": "SHIN-ONOMICHI"
    },
    {
        "n": "Sakura 758",
        "d": "Down",
        "b": false,
        "s": "FUKUYAMA"
    },
    {
        "n": "Nozomi 182",
        "d": "Down",
        "b": true,
        "s": "SHIN-KURASHIKI",
        "s_b": "OKAYAMA"
    },
    {
        "n": "Nozomi 42",
        "d": "Down",
        "b": false,
        "s": "OKAYAMA"
    },
    {
        "n": "Nozomi 102",
        "d": "Down",
        "b": true,
        "s": "OKAYAMA",
        "s_b": "AIOI"
    },
    {
        "n": "Nozomi 180",
        "d": "Down",
        "b": true,
        "s": "OKAYAMA",
        "s_b": "AIOI"
    },
    {
        "n": "Kodama 956",
        "d": "Down",
        "b": false,
        "s": "OKAYAMA"
    },
    {
        "n": "Nozomi 40",
        "d": "Down",
        "b": true,
        "s": "AIOI",
        "s_b": "HIMEJI"
    },
    {
        "n": "Hikari 718",
        "d": "Down",
        "b": false,
        "s": "AIOI"
    },
    {
        "n": "Sakura 794",
        "d": "Down",
        "b": true,
        "s": "HIMEJI",
        "s_b": "NISHI-AKASHI"
    },
    {
        "n": "Nozomi 178",
        "d": "Down",
        "b": true,
        "s": "NISHI-AKASHI",
        "s_b": "SHIN-KOBE"
    },
    {
        "n": "Kodama 954",
        "d": "Down",
        "b": false,
        "s": "NISHI-AKASHI"
    },
    {
        "n": "Sakura 756",
        "d": "Down",
        "b": true,
        "s": "SHIN-KOBE",
        "s_b": "SHIN-OSAKA"
    },
    {
        "n": "Nozomi 38",
        "d": "Down",
        "b": false,
        "s": "SHIN-KOBE"
    },
    {
        "n": "Nozomi 176",
        "d": "Down",
        "b": false,
        "s": "SHIN-OSAKA"
    },
    {
        "n": "Nozomi 174",
        "d": "Down",
        "b": true,
        "s": "SHIN-OSAKA",
        "s_b": "KYOTO"
    },
    {
        "n": "Kodama 844",
        "d": "Down",
        "b": true,
        "s": "SHIN-OSAKA",
        "s_b": "KYOTO"
    },
    {
        "n": "Hikari 716",
        "d": "Down",
        "b": true,
        "s": "SHIN-OSAKA",
        "s_b": "KYOTO"
    },
    {
        "n": "Nozomi 100",
        "d": "Down",
        "b": true,
        "s": "KYOTO",
        "s_b": "MAIBARA"
    },
    {
        "n": "Nozomi 36",
        "d": "Down",
        "b": false,
        "s": "KYOTO"
    },
    {
        "n": "Nozomi 170",
        "d": "Down",
        "b": true,
        "s": "KYOTO",
        "s_b": "MAIBARA"
    },
    {
        "n": "Nozomi 454",
        "d": "Down",
        "b": true,
        "s": "KYOTO",
        "s_b": "MAIBARA"
    },
    {
        "n": "Nozomi 172",
        "d": "Down",
        "b": true,
        "s": "KYOTO",
        "s_b": "MAIBARA"
    },
    {
        "n": "Nozomi 446",
        "d": "Down",
        "b": true,
        "s": "MAIBARA",
        "s_b": "GIFU-HASHIMA"
    },
    {
        "n": "Nozomi 448",
        "d": "Down",
        "b": true,
        "s": "MAIBARA",
        "s_b": "GIFU-HASHIMA"
    },
    {
        "n": "Hikari 658",
        "d": "Down",
        "b": true,
        "s": "MAIBARA",
        "s_b": "GIFU-HASHIMA"
    },
    {
        "n": "Nozomi 168",
        "d": "Down",
        "b": true,
        "s": "GIFU-HASHIMA",
        "s_b": "NAGOYA"
    },
    {
        "n": "Hayabusa 34",
        "d": "Up",
        "b": true,
        "s": "SHICHINOHE-TOWADA",
        "s_b": "HACHINOHE"
    },
    {
        "n": "Hayabusa 62",
        "d": "Up",
        "b": true,
        "s": "IWATE-NUMAKUNAI",
        "s_b": "MORIOKA"
    },
    {
        "n": "Komachi 32",
        "d": "Up",
        "b": true,
        "s": "SHIN-HANAMAKI",
        "s_b": "KITAKAMI"
    },
    {
        "n": "Hayabusa 32",
        "d": "Up",
        "b": true,
        "s": "SHIN-HANAMAKI",
        "s_b": "KITAKAMI"
    },
    {
        "n": "Yamabiko 170",
        "d": "Up",
        "b": false,
        "s": "KITAKAMI"
    },
    {
        "n": "Yamabiko 64",
        "d": "Up",
        "b": false,
        "s": "KURIKOMA-KOGEN"
    },
    {
        "n": "Hayabusa 30",
        "d": "Up",
        "b": true,
        "s": "FURUKAWA",
        "s_b": "SENDAI"
    },
    {
        "n": "Komachi 60",
        "d": "Up",
        "b": true,
        "s": "SENDAI",
        "s_b": "SHIROISHIZAO"
    },
    {
        "n": "Hayabusa 60",
        "d": "Up",
        "b": true,
        "s": "SENDAI",
        "s_b": "SHIROISHIZAO"
    },
    {
        "n": "Yamabiko 150",
        "d": "Up",
        "b": true,
        "s": "SHIROISHIZAO",
        "s_b": "FUKUSHIMA"
    },
    {
        "n": "Tsubasa 148",
        "d": "Up",
        "b": false,
        "s": "FUKUSHIMA"
    },
    {
        "n": "Yamabiko 62",
        "d": "Up",
        "b": true,
        "s": "FUKUSHIMA",
        "s_b": "KORIYAMA"
    },
    {
        "n": "Yamabiko 148",
        "d": "Up",
        "b": false,
        "s": "FUKUSHIMA"
    },
    {
        "n": "Komachi 28",
        "d": "Up",
        "b": true,
        "s": "KORIYAMA",
        "s_b": "SHIN-SHIRAKAWA"
    },
    {
        "n": "Hayabusa 28",
        "d": "Up",
        "b": true,
        "s": "KORIYAMA",
        "s_b": "SHIN-SHIRAKAWA"
    },
    {
        "n": "Hayabusa 86",
        "d": "Up",
        "b": true,
        "s": "SHIN-SHIRAKAWA",
        "s_b": "NASUSHIOBARA"
    },
    {
        "n": "Yamabiko 216",
        "d": "Up",
        "b": true,
        "s": "SHIN-SHIRAKAWA",
        "s_b": "NASUSHIOBARA"
    },
    {
        "n": "Nasuno 294",
        "d": "Up",
        "b": true,
        "s": "NASUSHIOBARA",
        "s_b": "UTSUNOMIYA"
    },
    {
        "n": "Tsubasa 146",
        "d": "Up",
        "b": true,
        "s": "UTSUNOMIYA",
        "s_b": "OYAMA"
    },
    {
        "n": "Yamabiko 146",
        "d": "Up",
        "b": true,
        "s": "UTSUNOMIYA",
        "s_b": "OYAMA"
    },
    {
        "n": "Yamabiko 166",
        "d": "Up",
        "b": true,
        "s": "UTSUNOMIYA",
        "s_b": "OYAMA"
    },
    {
        "n": "Komachi 26",
        "d": "Up",
        "b": true,
        "s": "OYAMA",
        "s_b": "OMIYA"
    },
    {
        "n": "Tsubasa 188",
        "d": "Up",
        "b": true,
        "s": "OYAMA",
        "s_b": "OMIYA"
    },
    {
        "n": "Hayabusa 26",
        "d": "Up",
        "b": true,
        "s": "OYAMA",
        "s_b": "OMIYA"
    },
    {
        "n": "Yamabiko 188",
        "d": "Up",
        "b": true,
        "s": "OYAMA",
        "s_b": "OMIYA"
    },
    {
        "n": "Komachi 24",
        "d": "Up",
        "b": true,
        "s": "OMIYA",
        "s_b": "UENO"
    },
    {
        "n": "Nasuno 278",
        "d": "Up",
        "b": true,
        "s": "OMIYA",
        "s_b": "UENO"
    },
    {
        "n": "Hayabusa 24",
        "d": "Up",
        "b": true,
        "s": "OMIYA",
        "s_b": "UENO"
    },
    {
        "n": "Yamabiko 60",
        "d": "Up",
        "b": false,
        "s": "OMIYA"
    },
    {
        "n": "Yamabiko 147",
        "d": "Down",
        "b": true,
        "s": "UENO",
        "s_b": "OMIYA"
    },
    {
        "n": "Hayabusa 63",
        "d": "Down",
        "b": true,
        "s": "UENO",
        "s_b": "OMIYA"
    },
    {
        "n": "Tsubasa 91",
        "d": "Down",
        "b": true,
        "s": "UENO",
        "s_b": "OMIYA"
    },
    {
        "n": "Yamabiko 213",
        "d": "Down",
        "b": true,
        "s": "OYAMA",
        "s_b": "UTSUNOMIYA"
    },
    {
        "n": "Hayabusa 33",
        "d": "Down",
        "b": true,
        "s": "OYAMA",
        "s_b": "UTSUNOMIYA"
    },
    {
        "n": "Komachi 33",
        "d": "Down",
        "b": true,
        "s": "OYAMA",
        "s_b": "UTSUNOMIYA"
    },
    {
        "n": "Toki 330",
        "d": "Up",
        "b": true,
        "s": "NAGAOKA",
        "s_b": "URASA"
    },
    {
        "n": "Toki 76",
        "d": "Up",
        "b": true,
        "s": "URASA",
        "s_b": "ECHIGO-YUZAWA"
    },
    {
        "n": "Toki 74",
        "d": "Up",
        "b": false,
        "s": "ECHIGO-YUZAWA"
    },
    {
        "n": "Toki 330",
        "d": "Down",
        "b": true,
        "s": "NAGAOKA",
        "s_b": "URASA"
    },
    {
        "n": "Toki 76",
        "d": "Down",
        "b": true,
        "s": "URASA",
        "s_b": "ECHIGO-YUZAWA"
    },
    {
        "n": "Toki 74",
        "d": "Down",
        "b": false,
        "s": "ECHIGO-YUZAWA"
    },
    {
        "n": "Toki 328",
        "d": "Down",
        "b": true,
        "s": "HONJOWASEDA",
        "s_b": "KUMAGAYA"
    },
    {
        "n": "Tanigawa 412",
        "d": "Down",
        "b": true,
        "s": "OMIYA",
        "s_b": "UENO"
    },
    {
        "n": "Toki 326",
        "d": "Down",
        "b": false,
        "s": "UENO"
    },
    {
        "n": "Tsurugi 30",
        "d": "Up",
        "b": true,
        "s": "ECHIZEN-TAKEFU",
        "s_b": "FUKUI"
    },
    {
        "n": "Kagayaki 538",
        "d": "Up",
        "b": true,
        "s": "KOMATSU",
        "s_b": "KANAZAWA"
    },
    {
        "n": "Hakutaka 572",
        "d": "Up",
        "b": true,
        "s": "KANAZAWA",
        "s_b": "SHIN-TAKAOKA"
    },
    {
        "n": "Kagayaki 512",
        "d": "Up",
        "b": true,
        "s": "KANAZAWA",
        "s_b": "SHIN-TAKAOKA"
    },
    {
        "n": "Tsurugi 28",
        "d": "Up",
        "b": true,
        "s": "SHIN-TAKAOKA",
        "s_b": "TOYAMA"
    },
    {
        "n": "Hakutaka 570",
        "d": "Up",
        "b": true,
        "s": "ITOIGAWA",
        "s_b": "JOETSUMYOKO"
    },
    {
        "n": "Kagayaki 510",
        "d": "Up",
        "b": true,
        "s": "IIYAMA",
        "s_b": "NAGANO"
    },
    {
        "n": "Hakutaka 660",
        "d": "Up",
        "b": true,
        "s": "NAGANO",
        "s_b": "UEDA"
    },
    {
        "n": "Asama 626",
        "d": "Up",
        "b": true,
        "s": "KARUIZAWA",
        "s_b": "ANNAKAHARUNA"
    },
    {
        "n": "Hakutaka 568",
        "d": "Up",
        "b": true,
        "s": "ANNAKAHARUNA",
        "s_b": "TAKASAKI"
    },
    {
        "n": "Asama 621",
        "d": "Down",
        "b": true,
        "s": "TOKYO",
        "s_b": "UENO"
    },
    {
        "n": "Kagayaki 511",
        "d": "Down",
        "b": true,
        "s": "OMIYA",
        "s_b": "KUMAGAYA"
    },
    {
        "n": "Hakutaka 571",
        "d": "Down",
        "b": false,
        "s": "OMIYA"
    },
    {
        "n": "Asama 619",
        "d": "Down",
        "b": false,
        "s": "ANNAKAHARUNA"
    },
    {
        "n": "Hakutaka 645",
        "d": "Down",
        "b": true,
        "s": "UEDA",
        "s_b": "NAGANO"
    },
    {
        "n": "Hakutaka 569",
        "d": "Down",
        "b": true,
        "s": "NAGANO",
        "s_b": "IIYAMA"
    },
    {
        "n": "Kagayaki 539",
        "d": "Down",
        "b": true,
        "s": "KUROBEUNAZUKIONSEN",
        "s_b": "TOYAMA"
    },
    {
        "n": "Hakutaka 567",
        "d": "Down",
        "b": true,
        "s": "TOYAMA",
        "s_b": "SHIN-TAKAOKA"
    },
    {
        "n": "Tsurugi 35",
        "d": "Down",
        "b": true,
        "s": "KANAZAWA",
        "s_b": "KOMATSU"
    },
    {
        "n": "Tsurugi 37",
        "d": "Down",
        "b": false,
        "s": "KANAZAWA"
    },
    {
        "n": "Hakutaka 565",
        "d": "Down",
        "b": true,
        "s": "FUKUI",
        "s_b": "ECHIZEN-TAKEFU"
    },
    {
        "n": "Tsurugi 33",
        "d": "Down",
        "b": true,
        "s": "ECHIZEN-TAKEFU",
        "s_b": "TSURUGA"
    },
    {
        "n": "Tsubame 364",
        "d": "Up",
        "b": true,
        "s": "SENDAI",
        "s_b": "IZUMI"
    },
    {
        "n": "Tsubame 328",
        "d": "Up",
        "b": true,
        "s": "SHIN-MINAMATA",
        "s_b": "SHIN-YATSUSHIRO"
    },
    {
        "n": "Sakura 768",
        "d": "Up",
        "b": true,
        "s": "SHIN-YATSUSHIRO",
        "s_b": "KUMAMOTO"
    },
    {
        "n": "Tsubame 364",
        "d": "Down",
        "b": true,
        "s": "SENDAI",
        "s_b": "IZUMI"
    },
    {
        "n": "Tsubame 328",
        "d": "Down",
        "b": true,
        "s": "SHIN-MINAMATA",
        "s_b": "SHIN-YATSUSHIRO"
    },
    {
        "n": "Sakura 768",
        "d": "Down",
        "b": true,
        "s": "SHIN-YATSUSHIRO",
        "s_b": "KUMAMOTO"
    },
    {
        "n": "KAMOME 46",
        "d": "Up",
        "b": true,
        "s": "SHIN-OMURA",
        "s_b": "URESHINO-ONSEN"
    },
    {
        "n": "KAMOME 46",
        "d": "Down",
        "b": true,
        "s": "SHIN-OMURA",
        "s_b": "URESHINO-ONSEN"
    },
    {
        "n": "Hayabusa 36",
        "d": "Up",
        "b": true,
        "s": "KIKONAI",
        "s_b": "OKUTSUGARU-IMABETSU"
    },
    {
        "n": "Hayabusa 25",
        "d": "Down",
        "b": false,
        "s": "OKUTSUGARU-IMABETSU"
    },
    {
        "n": "Tsubasa",
        "s": "YAMAGATA",
        "s_b": "TENDO",
        "b": true,
        "d": "Down"
    },
    {
        "n": "Tsubasa",
        "s": "YONEZAWA",
        "s_b": "TAKAHATA",
        "b": true,
        "d": "Down"
    },
    {
        "n": "Tsubasa",
        "s": "FUKUSHIMA",
        "s_b": "YONEZAWA",
        "b": true,
        "d": "Down"
    },
    {
        "n": "Tsubasa",
        "s": "KAMINOYAMA ONSEN",
        "s_b": "AKAYU",
        "b": true,
        "d": "Up"
    },
    {
        "n": "Tsubasa",
        "s": "AKAYU",
        "s_b": "KAMINOYAMA ONSEN",
        "b": true,
        "d": "Down"
    },
    {
        "n": "Tsubasa",
        "s": "SAKURANBO-HIGASHINE",
        "s_b": "TENDO",
        "b": true,
        "d": "Up"
    },
    {
        "n": "Komachi",
        "s": "KAKUNODATE",
        "s_b": "OMAGARI",
        "b": false,
        "d": "Down"
    },
    {
        "n": "Komachi",
        "s": "MORIOKA",
        "s_b": "TAZAWAKO",
        "b": true,
        "d": "Down"
    },
    {
        "n": "Komachi",
        "s": "MORIOKA",
        "s_b": "TAZAWAKO",
        "b": true,
        "d": "Down"
    },
    {
        "n": "Komachi",
        "s": "KAKUNODATE",
        "s_b": "TAZAWAKO",
        "b": true,
        "d": "Up"
    },
    {
        "n": "Komachi",
        "s": "AKITA",
        "s_b": "OMAGARI",
        "b": true,
        "d": "Up"
    }
]