[
    {
        "n": "Sakura 540",
        "d": "Up",
        "b": true,
        "s": "HAKATA",
        "s_b": "KOKURA"
    },
    {
        "n": "Kodama 842",
        "d": "Up",
        "b": true,
        "s": "HAKATA",
        "s_b": "KOKURA"
    },
    {
        "n": "Nozomi 4",
        "d": "Up",
        "b": true,
        "s": "ASA",
        "s_b": "SHIN-YAMAGUCHI"
    },
    {
        "n": "Kodama 840",
        "d": "Up",
        "b": true,
        "s": "ASA",
        "s_b": "SHIN-YAMAGUCHI"
    },
    {
        "n": "Kodama 838",
        "d": "Up",
        "b": false,
        "s": "TOKUYAMA"
    },
    {
        "n": "Hikari 590",
        "d": "Up",
        "b": true,
        "s": "SHIN-IWAKUNI",
        "s_b": "HIROSHIMA"
    },
    {
        "n": "Nozomi 2",
        "d": "Up",
        "b": true,
        "s": "HIROSHIMA",
        "s_b": "HIGASHIHIROSHIMA"
    },
    {
        "n": "Kodama 836",
        "d": "Up",
        "b": true,
        "s": "HIGASHIHIROSHIMA",
        "s_b": "MIHARA"
    },
    {
        "n": "Nozomi 78",
        "d": "Up",
        "b": true,
        "s": "FUKUYAMA",
        "s_b": "SHIN-KURASHIKI"
    },
    {
        "n": "Hikari 500",
        "d": "Up",
        "b": true,
        "s": "FUKUYAMA",
        "s_b": "SHIN-KURASHIKI"
    },
    {
        "n": "Nozomi 76",
        "d": "Up",
        "b": true,
        "s": "OKAYAMA",
        "s_b": "AIOI"
    },
    {
        "n": "Kodama 834",
        "d": "Up",
        "b": false,
        "s": "OKAYAMA"
    },
    {
        "n": "Kodama 832",
        "d": "Up",
        "b": false,
        "s": "HIMEJI"
    },
    {
        "n": "Nozomi 74",
        "d": "Up",
        "b": true,
        "s": "NISHI-AKASHI",
        "s_b": "SHIN-KOBE"
    },
    {
        "n": "Nozomi 214",
        "d": "Up",
        "b": true,
        "s": "SHIN-OSAKA",
        "s_b": "KYOTO"
    },
    {
        "n": "Nozomi 72",
        "d": "Up",
        "b": false,
        "s": "SHIN-OSAKA"
    },
    {
        "n": "Nozomi 288",
        "d": "Up",
        "b": true,
        "s": "KYOTO",
        "s_b": "MAIBARA"
    },
    {
        "n": "Nozomi 70",
        "d": "Up",
        "b": true,
        "s": "KYOTO",
        "s_b": "MAIBARA"
    },
    {
        "n": "Nozomi 290",
        "d": "Up",
        "b": true,
        "s": "KYOTO",
        "s_b": "MAIBARA"
    },
    {
        "n": "Hikari 636",
        "d": "Up",
        "b": true,
        "s": "KYOTO",
        "s_b": "MAIBARA"
    },
    {
        "n": "Nozomi 68",
        "d": "Up",
        "b": true,
        "s": "MAIBARA",
        "s_b": "GIFU-HASHIMA"
    },
    {
        "n": "Nozomi 66",
        "d": "Up",
        "b": true,
        "s": "GIFU-HASHIMA",
        "s_b": "NAGOYA"
    },
    {
        "n": "Hikari 634",
        "d": "Up",
        "b": true,
        "s": "GIFU-HASHIMA",
        "s_b": "NAGOYA"
    },
    {
        "n": "Nozomi 212",
        "d": "Up",
        "b": true,
        "s": "NAGOYA",
        "s_b": "MIKAWA-ANJO"
    },
    {
        "n": "Nozomi 282",
        "d": "Up",
        "b": true,
        "s": "MIKAWA-ANJO",
        "s_b": "TOYOHASHI"
    },
    {
        "n": "Kodama 700",
        "d": "Up",
        "b": true,
        "s": "MIKAWA-ANJO",
        "s_b": "TOYOHASHI"
    },
    {
        "n": "Nozomi 210",
        "d": "Up",
        "b": true,
        "s": "TOYOHASHI",
        "s_b": "HAMAMATSU"
    },
    {
        "n": "Hikari 632",
        "d": "Up",
        "b": false,
        "s": "TOYOHASHI"
    },
    {
        "n": "Nozomi 268",
        "d": "Up",
        "b": true,
        "s": "KAKEGAWA",
        "s_b": "SHIZUOKA"
    },
    {
        "n": "Kodama 818",
        "d": "Up",
        "b": false,
        "s": "KAKEGAWA"
    },
    {
        "n": "Hikari 630",
        "d": "Up",
        "b": true,
        "s": "KAKEGAWA",
        "s_b": "SHIZUOKA"
    },
    {
        "n": "Kodama 812",
        "d": "Up",
        "b": true,
        "s": "SHIZUOKA",
        "s_b": "SHIN-FUJI"
    },
    {
        "n": "Kodama 814",
        "d": "Up",
        "b": false,
        "s": "SHIZUOKA"
    },
    {
        "n": "Kodama 808",
        "d": "Up",
        "b": true,
        "s": "MISHIMA",
        "s_b": "ATAMI"
    },
    {
        "n": "Kodama 806",
        "d": "Up",
        "b": true,
        "s": "ATAMI",
        "s_b": "ODAWARA"
    },
    {
        "n": "Kodama 804",
        "d": "Up",
        "b": true,
        "s": "ODAWARA",
        "s_b": "SHIN-YOKOHAMA"
    },
    {
        "n": "Kodama 802",
        "d": "Up",
        "b": true,
        "s": "SHIN-YOKOHAMA",
        "s_b": "SHINAGAWA"
    },
    {
        "n": "Hikari 501",
        "d": "Down",
        "b": false,
        "s": "SHINAGAWA"
    },
    {
        "n": "Kodama 703",
        "d": "Down",
        "b": true,
        "s": "SHINAGAWA",
        "s_b": "SHIN-YOKOHAMA"
    },
    {
        "n": "Nozomi 107",
        "d": "Down",
        "b": true,
        "s": "SHINAGAWA",
        "s_b": "SHIN-YOKOHAMA"
    },
    {
        "n": "Nozomi 105",
        "d": "Down",
        "b": true,
        "s": "SHIN-YOKOHAMA",
        "s_b": "ODAWARA"
    },
    {
        "n": "Nozomi 7",
        "d": "Down",
        "b": true,
        "s": "SHIN-YOKOHAMA",
        "s_b": "ODAWARA"
    },
    {
        "n": "Kodama 701",
        "d": "Down",
        "b": true,
        "s": "ODAWARA",
        "s_b": "ATAMI"
    },
    {
        "n": "Nozomi 5",
        "d": "Down",
        "b": true,
        "s": "ATAMI",
        "s_b": "MISHIMA"
    },
    {
        "n": "Hikari 631",
        "d": "Down",
        "b": true,
        "s": "MISHIMA",
        "s_b": "SHIN-FUJI"
    },
    {
        "n": "Kodama 767",
        "d": "Down",
        "b": true,
        "s": "SHIN-FUJI",
        "s_b": "SHIZUOKA"
    },
    {
        "n": "Nozomi 287",
        "d": "Down",
        "b": true,
        "s": "SHIN-FUJI",
        "s_b": "SHIZUOKA"
    },
    {
        "n": "Nozomi 3",
        "d": "Down",
        "b": true,
        "s": "SHIZUOKA",
        "s_b": "KAKEGAWA"
    },
    {
        "n": "Kodama 765",
        "d": "Down",
        "b": false,
        "s": "HAMAMATSU"
    },
    {
        "n": "Nozomi 99",
        "d": "Down",
        "b": true,
        "s": "HAMAMATSU",
        "s_b": "TOYOHASHI"
    },
    {
        "n": "Nozomi 1",
        "d": "Down",
        "b": true,
        "s": "HAMAMATSU",
        "s_b": "TOYOHASHI"
    },
    {
        "n": "Hikari 533",
        "d": "Down",
        "b": true,
        "s": "TOYOHASHI",
        "s_b": "MIKAWA-ANJO"
    },
    {
        "n": "Kodama 763",
        "d": "Down",
        "b": false,
        "s": "NAGOYA"
    },
    {
        "n": "Nozomi 277",
        "d": "Down",
        "b": true,
        "s": "NAGOYA",
        "s_b": "GIFU-HASHIMA"
    },
    {
        "n": "Kodama 761",
        "d": "Down",
        "b": true,
        "s": "GIFU-HASHIMA",
        "s_b": "MAIBARA"
    },
    {
        "n": "Hikari 531",
        "d": "Down",
        "b": true,
        "s": "MAIBARA",
        "s_b": "KYOTO"
    },
    {
        "n": "Kodama 839",
        "d": "Down",
        "b": true,
        "s": "SHIN-OSAKA",
        "s_b": "SHIN-KOBE"
    },
    {
        "n": "Nozomi 275",
        "d": "Down",
        "b": false,
        "s": "SHIN-OSAKA"
    },
    {
        "n": "Sakura 543",
        "d": "Down",
        "b": true,
        "s": "NISHI-AKASHI",
        "s_b": "HIMEJI"
    },
    {
        "n": "Sakura 541",
        "d": "Down",
        "b": true,
        "s": "AIOI",
        "s_b": "OKAYAMA"
    },
    {
        "n": "Hikari 591",
        "d": "Down",
        "b": true,
        "s": "OKAYAMA",
        "s_b": "SHIN-KURASHIKI"
    },
    {
        "n": "Mizuho 601",
        "d": "Down",
        "b": true,
        "s": "SHIN-ONOMICHI",
        "s_b": "MIHARA"
    },
    {
        "n": "Kodama 833",
        "d": "Down",
        "b": false,
        "s": "MIHARA"
    },
    {
        "n": "Kodama 831",
        "d": "Down",
        "b": false,
        "s": "HIROSHIMA"
    },
    {
        "n": "Kodama 781",
        "d": "Down",
        "b": true,
        "s": "SHIN-IWAKUNI",
        "s_b": "TOKUYAMA"
    },
    {
        "n": "Sakura 401",
        "d": "Down",
        "b": true,
        "s": "TOKUYAMA",
        "s_b": "SHIN-YAMAGUCHI"
    },
    {
        "n": "Kodama 777",
        "d": "Down",
        "b": true,
        "s": "SHIN-YAMAGUCHI",
        "s_b": "ASA"
    },
    {
        "n": "Kodama 775",
        "d": "Down",
        "b": true,
        "s": "SHIN-SHIMONOSEKI",
        "s_b": "KOKURA"
    },
    {
        "n": "Kodama 773",
        "d": "Down",
        "b": true,
        "s": "KOKURA",
        "s_b": "HAKATA"
    },
    {
        "n": "Hayabusa 8",
        "d": "Up",
        "b": true,
        "s": "SHICHINOHE-TOWADA",
        "s_b": "HACHINOHE"
    },
    {
        "n": "Hayabusa 4",
        "d": "Up",
        "b": false,
        "s": "MORIOKA"
    },
    {
        "n": "Yamabiko 50",
        "d": "Up",
        "b": true,
        "s": "MORIOKA",
        "s_b": "SHIN-HANAMAKI"
    },
    {
        "n": "Yamabiko 94",
        "d": "Up",
        "b": true,
        "s": "ICHINOSEKI",
        "s_b": "KURIKOMA-KOGEN"
    },
    {
        "n": "Hayabusa 102",
        "d": "Up",
        "b": true,
        "s": "FURUKAWA",
        "s_b": "SENDAI"
    },
    {
        "n": "Yamabiko 206",
        "d": "Up",
        "b": true,
        "s": "SHIROISHIZAO",
        "s_b": "FUKUSHIMA"
    },
    {
        "n": "Yamabiko 204",
        "d": "Up",
        "b": true,
        "s": "KORIYAMA",
        "s_b": "SHIN-SHIRAKAWA"
    },
    {
        "n": "Hayabusa 2",
        "d": "Up",
        "b": true,
        "s": "SHIN-SHIRAKAWA",
        "s_b": "NASUSHIOBARA"
    },
    {
        "n": "Yamabiko 202",
        "d": "Up",
        "b": true,
        "s": "NASUSHIOBARA",
        "s_b": "UTSUNOMIYA"
    },
    {
        "n": "Nasuno 260",
        "d": "Up",
        "b": true,
        "s": "UTSUNOMIYA",
        "s_b": "OYAMA"
    },
    {
        "n": "Nasuno 262",
        "d": "Up",
        "b": true,
        "s": "UTSUNOMIYA",
        "s_b": "OYAMA"
    },
    {
        "n": "Nasuno 258",
        "d": "Up",
        "b": true,
        "s": "OYAMA",
        "s_b": "OMIYA"
    },
    {
        "n": "Nasuno 254",
        "d": "Up",
        "b": true,
        "s": "OMIYA",
        "s_b": "UENO"
    },
    {
        "n": "Nasuno 256",
        "d": "Up",
        "b": true,
        "s": "OMIYA",
        "s_b": "UENO"
    },
    {
        "n": "Hayabusa 51",
        "d": "Down",
        "b": true,
        "s": "UENO",
        "s_b": "OMIYA"
    },
    {
        "n": "Nasuno 251",
        "d": "Down",
        "b": true,
        "s": "UENO",
        "s_b": "OMIYA"
    },
    {
        "n": "Komachi 51",
        "d": "Down",
        "b": true,
        "s": "UENO",
        "s_b": "OMIYA"
    },
    {
        "n": "Yamabiko 203",
        "d": "Down",
        "b": true,
        "s": "OMIYA",
        "s_b": "OYAMA"
    },
    {
        "n": "Hayabusa 1",
        "d": "Down",
        "b": true,
        "s": "OMIYA",
        "s_b": "OYAMA"
    },
    {
        "n": "Komachi 1",
        "d": "Down",
        "b": true,
        "s": "OMIYA",
        "s_b": "OYAMA"
    },
    {
        "n": "Yamabiko 201",
        "d": "Down",
        "b": true,
        "s": "OYAMA",
        "s_b": "UTSUNOMIYA"
    },
    {
        "n": "Tsubasa 121",
        "d": "Down",
        "b": true,
        "s": "UTSUNOMIYA",
        "s_b": "NASUSHIOBARA"
    },
    {
        "n": "Yamabiko 51",
        "d": "Down",
        "b": true,
        "s": "NASUSHIOBARA",
        "s_b": "SHIN-SHIRAKAWA"
    },
    {
        "n": "Hayabusa 49",
        "d": "Down",
        "b": true,
        "s": "KORIYAMA",
        "s_b": "FUKUSHIMA"
    },
    {
        "n": "Yamabiko 291",
        "d": "Down",
        "b": true,
        "s": "FUKUSHIMA",
        "s_b": "SHIROISHIZAO"
    },
    {
        "n": "Yamabiko 97",
        "d": "Down",
        "b": true,
        "s": "SENDAI",
        "s_b": "FURUKAWA"
    },
    {
        "n": "Hayabusa 95",
        "d": "Down",
        "b": false,
        "s": "ICHINOSEKI"
    },
    {
        "n": "Komachi 95",
        "d": "Down",
        "b": false,
        "s": "ICHINOSEKI"
    },
    {
        "n": "Hayate 93",
        "d": "Down",
        "b": true,
        "s": "IWATE-NUMAKUNAI",
        "s_b": "NINOHE"
    },
    {
        "n": "Toki 304",
        "d": "Up",
        "b": true,
        "s": "NIIGATA",
        "s_b": "TSUBAMESANJO"
    },
    {
        "n": "Toki 302",
        "d": "Up",
        "b": true,
        "s": "NAGAOKA",
        "s_b": "URASA"
    },
    {
        "n": "Toki 300",
        "d": "Up",
        "b": true,
        "s": "JOMO-KOGEN",
        "s_b": "TAKASAKI"
    },
    {
        "n": "Tanigawa 474",
        "d": "Up",
        "b": true,
        "s": "HONJOWASEDA",
        "s_b": "KUMAGAYA"
    },
    {
        "n": "Tanigawa 472",
        "d": "Up",
        "b": true,
        "s": "OMIYA",
        "s_b": "UENO"
    },
    {
        "n": "Tanigawa 400",
        "d": "Up",
        "b": false,
        "s": "OMIYA"
    },
    {
        "n": "Tanigawa 470",
        "d": "Up",
        "b": true,
        "s": "UENO",
        "s_b": "TOKYO"
    },
    {
        "n": "Toki 303",
        "d": "Down",
        "b": true,
        "s": "UENO",
        "s_b": "OMIYA"
    },
    {
        "n": "Tanigawa 73",
        "d": "Down",
        "b": true,
        "s": "OMIYA",
        "s_b": "KUMAGAYA"
    },
    {
        "n": "Tanigawa 401",
        "d": "Down",
        "b": true,
        "s": "OMIYA",
        "s_b": "KUMAGAYA"
    },
    {
        "n": "Toki 301",
        "d": "Down",
        "b": true,
        "s": "TAKASAKI",
        "s_b": "JOMO-KOGEN"
    },
    {
        "n": "Toki 481",
        "d": "Down",
        "b": true,
        "s": "ECHIGO-YUZAWA",
        "s_b": "URASA"
    },
    {
        "n": "Toki 491",
        "d": "Down",
        "b": false,
        "s": "TSUBAMESANJO"
    },
    {
        "n": "Tsurugi 62",
        "d": "Up",
        "b": true,
        "s": "FUKUI",
        "s_b": "AWARAONSEN"
    },
    {
        "n": "Kagayaki 502",
        "d": "Up",
        "b": true,
        "s": "KANAZAWA",
        "s_b": "SHIN-TAKAOKA"
    },
    {
        "n": "Tsurugi 60",
        "d": "Up",
        "b": true,
        "s": "SHIN-TAKAOKA",
        "s_b": "TOYAMA"
    },
    {
        "n": "Hakutaka 552",
        "d": "Up",
        "b": true,
        "s": "ITOIGAWA",
        "s_b": "JOETSUMYOKO"
    },
    {
        "n": "Kagayaki 500",
        "d": "Up",
        "b": true,
        "s": "NAGANO",
        "s_b": "UEDA"
    },
    {
        "n": "Asama 604",
        "d": "Up",
        "b": true,
        "s": "SAKUDAIRA",
        "s_b": "KARUIZAWA"
    },
    {
        "n": "Asama 602",
        "d": "Up",
        "b": true,
        "s": "TAKASAKI",
        "s_b": "HONJOWASEDA"
    },
    {
        "n": "Asama 600",
        "d": "Up",
        "b": true,
        "s": "KUMAGAYA",
        "s_b": "OMIYA"
    },
    {
        "n": "Asama 601",
        "d": "Down",
        "b": true,
        "s": "UENO",
        "s_b": "OMIYA"
    },
    {
        "n": "Hakutaka 551",
        "d": "Down",
        "b": true,
        "s": "HONJOWASEDA",
        "s_b": "TAKASAKI"
    },
    {
        "n": "Kagayaki 501",
        "d": "Down",
        "b": true,
        "s": "ANNAKAHARUNA",
        "s_b": "KARUIZAWA"
    },
    {
        "n": "Asama 699",
        "d": "Down",
        "b": false,
        "s": "SAKUDAIRA"
    },
    {
        "n": "Hakutaka 591",
        "d": "Down",
        "b": true,
        "s": "KUROBEUNAZUKIONSEN",
        "s_b": "TOYAMA"
    },
    {
        "n": "Tsurugi 5",
        "d": "Down",
        "b": true,
        "s": "KANAZAWA",
        "s_b": "KOMATSU"
    },
    {
        "n": "Tsurugi 3",
        "d": "Down",
        "b": false,
        "s": "FUKUI"
    },
    {
        "n": "Tsubame 308",
        "d": "Up",
        "b": true,
        "s": "KAGOSHIMA-CHUO",
        "s_b": "SENDAI"
    },
    {
        "n": "Sakura 542",
        "d": "Up",
        "b": true,
        "s": "SENDAI",
        "s_b": "IZUMI"
    },
    {
        "n": "Tsubame 306",
        "d": "Up",
        "b": true,
        "s": "IZUMI",
        "s_b": "SHIN-MINAMATA"
    },
    {
        "n": "Mizuho 600",
        "d": "Up",
        "b": true,
        "s": "SHIN-YATSUSHIRO",
        "s_b": "KUMAMOTO"
    },
    {
        "n": "Tsubame 302",
        "d": "Up",
        "b": true,
        "s": "KUMAMOTO",
        "s_b": "SHIN-TAMANA"
    },
    {
        "n": "Sakura 400",
        "d": "Up",
        "b": true,
        "s": "SHIN-TAMANA",
        "s_b": "SHIN-OMUTA"
    },
    {
        "n": "Tsubame 300",
        "d": "Up",
        "b": true,
        "s": "SHIN-TOSU",
        "s_b": "HAKATA"
    },
    {
        "n": "Tsubame 309",
        "d": "Down",
        "b": true,
        "s": "CHIKUGO-FUNAGOYA",
        "s_b": "SHIN-OMUTA"
    },
    {
        "n": "Tsubame 307",
        "d": "Down",
        "b": true,
        "s": "KUMAMOTO",
        "s_b": "SHIN-YATSUSHIRO"
    },
    {
        "n": "Tsubame 305",
        "d": "Down",
        "b": true,
        "s": "IZUMI",
        "s_b": "SENDAI"
    },
    {
        "n": "KAMOME 4",
        "d": "Up",
        "b": true,
        "s": "ISAHAYA",
        "s_b": "SHIN-OMURA"
    },
    {
        "n": "KAMOME 1",
        "d": "Down",
        "b": false,
        "s": "URESHINO-ONSEN"
    },
    {
        "n": "Hayabusa 10",
        "d": "Up",
        "b": true,
        "s": "KIKONAI",
        "s_b": "OKUTSUGARU-IMABETSU"
    },
    {
        "n": "Hayate 91",
        "d": "Down",
        "b": true,
        "s": "OKUTSUGARU-IMABETSU",
        "s_b": "KIKONAI"
    },
    {
        "n": "Tsubasa",
        "s": "AKAYU",
        "s_b": "KAMINOYAMA ONSEN",
        "b": true,
        "d": "Down"
    },
    {
        "n": "Tsubasa",
        "s": "TENDO",
        "s_b": "SAKURANBO-HIGASHINE",
        "b": true,
        "d": "Down"
    },
    {
        "n": "Tsubasa",
        "s": "MURAYAMA",
        "s_b": "SAKURANBO-HIGASHINE",
        "b": true,
        "d": "Up"
    },
    {
        "n": "Tsubasa",
        "s": "SHINJO",
        "s_b": "OISHIDA",
        "b": true,
        "d": "Up"
    }
]